Boa/__init__.py
Boa/__startup__.py
Boa/parallel/__init__.py
Boa/parallel/abc/__init__.py
Boa/parallel/abc/future.py
Boa/parallel/abc/pool.py
Boa/parallel/exceptions.py
Boa/parallel/logger.py
Boa/parallel/process/__init__.py
Boa/parallel/process/decorators.py
Boa/parallel/process/environment.py
Boa/parallel/process/pool.py
Boa/parallel/process/primitives/__init__.py
Boa/parallel/process/primitives/manager_process.py
Boa/parallel/process/primitives/process.py
Boa/parallel/process/primitives/python_process.py
Boa/parallel/process/primitives/resource_manager.py
Boa/parallel/process/primitives/utils.py
Boa/parallel/process/primitives/workers.py
Boa/parallel/thread/__init__.py
Boa/parallel/thread/decorators.py
Boa/parallel/thread/future.py
Boa/parallel/thread/primitives/__init__.py
Boa/parallel/thread/primitives/deamon.py
Boa/parallel/thread/primitives/nephilim.py
Boa/parallel/thread/synchronization.py
Boa/pipes.py
Boa/signal.py
Boa.pth
boa_lib-1.4.dist-info/LICENSE
boa_lib-1.4.dist-info/METADATA
boa_lib-1.4.dist-info/WHEEL
boa_lib-1.4.dist-info/RECORD
