Metadata-Version: 2.1
Name: boa_lib
Version: 1.4
Summary: A Python library with advanced system tools.
Home-page: https://github.com/MrVoustache/Boa
License: MIT
Author: Vincent Raulin
Author-email: vincent.raulin.n7@gmail.com
Classifier: License :: OSI Approved :: MIT License
Classifier: Operating System :: OS Independent
Classifier: Programming Language :: Python :: 2
Classifier: Programming Language :: Python :: 2.7
Classifier: Programming Language :: Python :: 3
Classifier: Programming Language :: Python :: 3.4
Classifier: Programming Language :: Python :: 3.5
Classifier: Programming Language :: Python :: 3.6
Classifier: Programming Language :: Python :: 3.7
Classifier: Programming Language :: Python :: 3.8
Classifier: Programming Language :: Python :: 3.9
Classifier: Programming Language :: Python :: 3.10
Classifier: Programming Language :: Python :: 3.11
Classifier: Programming Language :: Python :: 3.12
Classifier: Programming Language :: Python :: 3.13
Requires-Dist: viper_lib (>=1.3,<2.0)
Project-URL: Repository, https://github.com/MrVoustache/Boa
